Wtp/__init__.py
Wtp-0.0.6.1.dist-info/METADATA
Wtp-0.0.6.1.dist-info/RECORD
Wtp-0.0.6.1.dist-info/WHEEL
Wtp-0.0.6.1.dist-info/top_level.txt
