Metadata-Version: 2.1
Name: Wtp
Version: 0.0.6.1
Summary: Whatsapp chat analyzer with Python
Home-page: https://github.com/carlosniquini/Wtp
Author: Carlos Niquini
License: UNKNOWN
Platform: UNKNOWN
Classifier: Programming Language :: Python
Classifier: Programming Language :: Python :: 2.7
Classifier: Programming Language :: Python :: 3
Classifier: Programming Language :: Python :: 3.4
Classifier: Programming Language :: Python :: 3.5
Classifier: Programming Language :: Python :: 3.6
Classifier: License :: OSI Approved :: MIT License
Classifier: Operating System :: OS Independent
Requires-Dist: matplotlib
Requires-Dist: numpy
